certora_cli/__init__.py
certora_cli/certoraBuild.py
certora_cli/certoraCloudIO.py
certora_cli/certoraCollectRunMetadata.py
certora_cli/certoraConfigIO.py
certora_cli/certoraDualArg.py
certora_cli/certoraJobList.py
certora_cli/certoraLogging.py
certora_cli/certoraNodeFilters.py
certora_cli/certoraRun.py
certora_cli/certoraTester.py
certora_cli/certoraType.py
certora_cli/certoraUtils.py
certora_jars/Typechecker.jar
certora_jars/__init__.py
certora_cli_maker_structs_staging-3.0.4.dist-info/LICENSE
certora_cli_maker_structs_staging-3.0.4.dist-info/METADATA
certora_cli_maker_structs_staging-3.0.4.dist-info/WHEEL
certora_cli_maker_structs_staging-3.0.4.dist-info/entry_points.txt
certora_cli_maker_structs_staging-3.0.4.dist-info/top_level.txt
certora_cli_maker_structs_staging-3.0.4.dist-info/RECORD
